setup.py
seolint/__init__.py
seolint.egg-info/PKG-INFO
seolint.egg-info/SOURCES.txt
seolint.egg-info/dependency_links.txt
seolint.egg-info/entry_points.txt
seolint.egg-info/not-zip-safe
seolint.egg-info/requires.txt
seolint.egg-info/top_level.txt