Metadata-Version: 1.0
Name: seolint
Version: 0.2
Summary: SEO linting tool.
Home-page: http://github.com/storborg/seolint
Author: Scott Torborg
Author-email: storborg@mit.edu
License: MIT
Keywords: seo keywords crawl search tags ranking
Platform: UNKNOWN
Classifier: License :: OSI Approved :: MIT License
Classifier: Programming Language :: Python :: 2.7
